swaggerpetstore/__init__.py
swaggerpetstore/api_helper.py
swaggerpetstore/configuration.py
swaggerpetstore/swaggerpetstore_client.py
swaggerpetstore/controllers/__init__.py
swaggerpetstore/controllers/authentication_controller.py
swaggerpetstore/controllers/balances_controller.py
swaggerpetstore/controllers/base_controller.py
swaggerpetstore/controllers/beneficiary_bank_accounts_controller.py
swaggerpetstore/controllers/payments_controller.py
swaggerpetstore/controllers/pet_controller.py
swaggerpetstore/controllers/quotes_controller.py
swaggerpetstore/controllers/settlement_calendars_controller.py
swaggerpetstore/controllers/statements_controller.py
swaggerpetstore/controllers/store_controller.py
swaggerpetstore/controllers/transactions_controller.py
swaggerpetstore/controllers/user_controller.py
swaggerpetstore/controllers/users_controller.py
swaggerpetstore/exceptions/__init__.py
swaggerpetstore/exceptions/api_exception.py
swaggerpetstore/exceptions/validation_exception.py
swaggerpetstore/http/__init__.py
swaggerpetstore/http/http_call_back.py
swaggerpetstore/http/http_method_enum.py
swaggerpetstore/http/http_request.py
swaggerpetstore/http/http_response.py
swaggerpetstore/http/auth/__init__.py
swaggerpetstore/http/auth/custom_header_authentication.py
swaggerpetstore/models/__init__.py
swaggerpetstore/models/access_token_response.py
swaggerpetstore/models/account_balance.py
swaggerpetstore/models/action_1_enum.py
swaggerpetstore/models/action_enum.py
swaggerpetstore/models/additional_data.py
swaggerpetstore/models/additional_field_with_validator.py
swaggerpetstore/models/additional_field_with_values.py
swaggerpetstore/models/additional_fields_list.py
swaggerpetstore/models/additional_information_enum.py
swaggerpetstore/models/address.py
swaggerpetstore/models/api_response.py
swaggerpetstore/models/bank_account.py
swaggerpetstore/models/bank_account_details.py
swaggerpetstore/models/bank_account_expected_settlement_request.py
swagger_petstore-1.0.6.dist-info/LICENSE
swagger_petstore-1.0.6.dist-info/METADATA
swagger_petstore-1.0.6.dist-info/WHEEL
swagger_petstore-1.0.6.dist-info/top_level.txt
swagger_petstore-1.0.6.dist-info/RECORD
